setup.py
distributions/Binomialdistribution.py
distributions/Gaussiandistribution.py
distributions/Generaldistribution.py
distributions/__init__.py
statcomp.egg-info/PKG-INFO
statcomp.egg-info/SOURCES.txt
statcomp.egg-info/dependency_links.txt
statcomp.egg-info/not-zip-safe
statcomp.egg-info/top_level.txt